[
	{
		"fileName":"1.jpg",

		"title":"Heaven of time",
		"desc":"Here he cones Here comes Spwwd Racer"
	},
	{
		"fileName":"2.jpg",

		"title":"Heaven of time",
		"desc":"Here he cones Here comes Spwwd Racer"
	}
	{
		"fileName":"3.jpg",

		"title":"Heaven of time",
		"desc":"Here he cones Here comes Spwwd Racer"
	}
	{
		"fileName":"4.jpg",

		"title":"Heaven of time",
		"desc":"Here he cones Here comes Spwwd Racer"
	}
	{
		"fileName":"5.jpg",

		"title":"Heaven of time",
		"desc":"Here he cones Here comes Spwwd Racer"
	}
	{
		"fileName":"6.jpg",

		"title":"Heaven of time",
		"desc":"Here he cones Here comes Spwwd Racer"
	}
	{
		"fileName":"7.jpg",

		"title":"Heaven of time",
		"desc":"Here he cones Here comes Spwwd Racer"
	}
	{
		"fileName":"8.jpg",

		"title":"Heaven of time",
		"desc":"Here he cones Here comes Spwwd Racer"
	}
]